firefly_business_rules/__init__.py
firefly_business_rules/application/__init__.py
firefly_business_rules/application/container.py
firefly_business_rules/application/service/__init__.py
firefly_business_rules/application/service/evaluate_rules.py
firefly_business_rules/domain/__init__.py
firefly_business_rules/domain/entity/__init__.py
firefly_business_rules/domain/entity/command.py
firefly_business_rules/domain/entity/rule_set.py
firefly_business_rules/domain/service/__init__.py
firefly_business_rules/domain/service/remove_illegal_property_keys.py
firefly_business_rules/domain/service/rules_engine.py
firefly_business_rules/infrastructure/__init__.py
firefly_business_rules/infrastructure/service/__init__.py
firefly_business_rules/infrastructure/service/venmo_rules_engine.py
firefly_business_rules/presentation/__init__.py
firefly_business_rules-0.1.11.dist-info/METADATA
firefly_business_rules-0.1.11.dist-info/WHEEL
firefly_business_rules-0.1.11.dist-info/entry_points.txt
firefly_business_rules-0.1.11.dist-info/top_level.txt
firefly_business_rules-0.1.11.dist-info/RECORD
