Metadata-Version: 2.1
Name: firefly-business-rules
Version: 0.1.11
Summary: Put project description here.
Home-page: UNKNOWN
Author: UNKNOWN
Author-email: UNKNOWN
License: UNKNOWN
Platform: UNKNOWN
Classifier: Programming Language :: Python :: 3.7
Classifier: Operating System :: OS Independent
Requires-Dist: business-rules (>=1.0.1)
Requires-Dist: firefly-dependency-injection (>=0.1)
Requires-Dist: firefly-framework (>=1.1.12)
